torrentool/__init__.py
torrentool/api.py
torrentool/bencode.py
torrentool/cli.py
torrentool/exceptions.py
torrentool/torrent.py
torrentool/utils.py
torrentool/repo/open_trackers.ini
torrentool-1.2.0.dist-info/AUTHORS
torrentool-1.2.0.dist-info/LICENSE
torrentool-1.2.0.dist-info/METADATA
torrentool-1.2.0.dist-info/WHEEL
torrentool-1.2.0.dist-info/entry_points.txt
torrentool-1.2.0.dist-info/top_level.txt
torrentool-1.2.0.dist-info/RECORD
